postgres_chat/__init__.py
postgres_chat/charts.py
postgres_chat/postgres_chat.py
postgres_chat/prompt_and_tools.py
postgres_chat-0.1.5.dist-info/LICENSE
postgres_chat-0.1.5.dist-info/METADATA
postgres_chat-0.1.5.dist-info/WHEEL
postgres_chat-0.1.5.dist-info/top_level.txt
postgres_chat-0.1.5.dist-info/RECORD
