Metadata-Version: 2.1
Name: postgres-chat
Version: 0.1.5
Summary: Retrieval-Augmented Generation Handler using PostgreSQL and OpenAI
Home-page: https://github.com/QuentinFuxa/postgres-chat
Author: Quentin Fuxa
Requires-Python: >=3.9
License-File: LICENSE
Requires-Dist: openai
Requires-Dist: pandas
Requires-Dist: psycopg2
Requires-Dist: sqlalchemy
Requires-Dist: plotly
